pitricks/__init__.py
pitricks/path.py
pitricks/odd_tools/__init__.py
pitricks/odd_tools/file_batch_replace.py
pitricks/odd_tools/method_chain/__init__.py
pitricks/odd_tools/method_chain/main.py
pitricks/operations/__init__.py
pitricks/operations/ops.py
pitricks/tmp/__init__.py
pitricks/tmp/classes/__init__.py
pitricks/tmp/classes/chain.py
pitricks/utils/__init__.py
pitricks/utils/clz.py
pitricks/utils/code_generater.py
pitricks/utils/daemon.py
pitricks/utils/handle_exp.py
pitricks/utils/lock.py
pitricks/utils/log.py
pitricks/utils/mp_workflow.py
pitricks/utils/path_ops.py
pitricks/utils/reflect.py
pitricks/utils/relative_import_everywhere.py
pitricks/utils/retry.py
pitricks/utils/sync.py
pitricks/utils/test.py
pitricks/utils/types.py
pitricks/utils/use_pool.py
pitricks-0.1.4.dist-info/LICENSE
pitricks-0.1.4.dist-info/METADATA
pitricks-0.1.4.dist-info/WHEEL
pitricks-0.1.4.dist-info/top_level.txt
pitricks-0.1.4.dist-info/RECORD
